<extensions>
	<details>
		<title lang="EN">GitHub only Repo (AF1)</title>
	</details>
	<applets>

		<applet name="DarkFlatSkinInstaller" version="1.2.0" target="fab4" maxTarget="*">
			<title lang="EN">Dark Flat Skin Installer</title>
			<desc lang="EN">This applet installs the Dark Flat Skin on your SB Touch.  More information, screenshots and FAQ on https://github.com/AF-1. See FAQ for information on known SB Touch issue.</desc>
			<url>http://af1.userspace.sosou.eu/lmsrepo/DarkFlatSkinInstaller-fab4-1.2.0.zip</url>
			<creator>AF</creator>
			<link>https://github.com/AF-1/#-dark-flat-skin-picoreplayer-squeezeplay-sb-touch</link>
			<sha>414640a717e662a8c218b0697a2f5727665c0827</sha>
		</applet>

	</applets>

	<plugins>
		<plugin name="PotPourri" category="tools" version="1.0.2" minTarget="8.4" maxTarget="*">
			<title lang="EN">PotPourri</title>
			<desc lang="EN">A collection of small features. Examples: change track order of saved/client playlists, set power-on volume level for players or time to turn off all players each day, export saved playlists to playlist files with custom file paths/extensions… Complete feature list, screenshots and more information on the GitHub page.</desc>
			<url>https://github.com/AF-1/lms-potpourri/releases/download/1.0.2/lms-potpourri-1.0.2.zip</url>
			<icon>https://raw.githubusercontent.com/AF-1/lms-potpourri/main/PotPourri/HTML/EN/plugins/PotPourri/html/images/ppt_icon_svg.png</icon>
			<creator>AF</creator>
			<link>https://github.com/AF-1/#-potpourri</link>
			<sha>48bd1ea941d9ab3db1a77c8b51f5f39b80fe84b9</sha>
		</plugin>
	</plugins>
</extensions>
